{"assets":{"C63222EF0668CF992BAA5256B77B9CF5":{"type":"texture","index":1,"assetRequest":{"type":"slide","state":"contents","slide":"none"},"url":{"native":"assets/DEE60BF3-6F44-4784-B127-C924500EE327.pdf"},"width":1024,"height":768},"CDAECF3C4A226A6B0C3893C2DB2E3B05":{"type":"texture","index":0,"assetRequest":{"type":"slide","state":"contents","slide":"none"},"url":{"native":"assets/DEE60BF3-6F44-4784-B127-C924500EE327.pdf"},"width":1024,"height":768}},"events":[{"effects":[{"beginTime":0,"baseLayer":{"animations":[],"initialState":{"affineTransform":[1,0,0,1,0,0],"masksToBounds":false,"rotation":0,"scale":1,"position":{"pointX":512,"pointY":384},"width":1024,"sublayerTransform":[1,0,0,0,0,1,0,0,0,0,1,0,0,0,0,1],"contentsRect":{"y":0,"x":0,"width":1,"height":1},"opacity":1,"edgeAntialiasingMask":251658240,"height":768,"hidden":false,"anchorPoint":{"pointX":0.5,"pointY":0.5}},"objectID":"0","layers":[{"animations":[],"initialState":{"affineTransform":[1,0,0,1,0,0],"masksToBounds":false,"rotation":0,"scale":1,"position":{"pointX":512,"pointY":384},"width":1024,"sublayerTransform":[1,0,0,0,0,1,0,0,0,0,1,-0.0004922987690640373,0,0,0,1],"contentsRect":{"y":0,"x":0,"width":1,"height":1},"opacity":1,"edgeAntialiasingMask":251658240,"height":768,"hidden":false,"anchorPoint":{"pointX":0.5,"pointY":0.5}},"layers":[{"animations":[],"layers":[],"texturedRectangle":{"isBackgroundTexture":false,"singleTextureOpacity":1,"textureType":0,"textBaseline":0,"textXHeight":0,"isVerticalText":false},"initialState":{"affineTransform":[1,0,0,1,0,0],"masksToBounds":false,"rotation":0,"scale":1,"position":{"pointX":512,"pointY":384},"width":1024,"sublayerTransform":[1,0,0,0,0,1,0,0,0,0,1,0,0,0,0,1],"contentsRect":{"y":0,"x":0,"width":1,"height":1},"opacity":1,"edgeAntialiasingMask":0,"height":768,"hidden":false,"anchorPoint":{"pointX":0.5,"pointY":0.5}},"texture":"C63222EF0668CF992BAA5256B77B9CF5"},{"animations":[{"timeOffset":0,"from":{"scalar":false},"beginTime":0,"repeatCount":0,"fillMode":"both","property":"hidden","autoreverses":false,"duration":0.01,"to":{"scalar":true}}],"layers":[],"texturedRectangle":{"isBackgroundTexture":false,"singleTextureOpacity":1,"textureType":0,"textBaseline":0,"textXHeight":0,"isVerticalText":false},"initialState":{"affineTransform":[1,0,0,1,0,0],"masksToBounds":false,"rotation":0,"scale":1,"position":{"pointX":512,"pointY":384},"width":1024,"sublayerTransform":[1,0,0,0,0,1,0,0,0,0,1,0,0,0,0,1],"contentsRect":{"y":0,"x":0,"width":1,"height":1},"opacity":1,"edgeAntialiasingMask":0,"height":768,"hidden":false,"anchorPoint":{"pointX":0.5,"pointY":0.5}},"texture":"CDAECF3C4A226A6B0C3893C2DB2E3B05"}]}]},"effects":[],"duration":0.01,"type":"transition","name":"none","objectID":"0"}],"automaticPlay":false,"hyperlinks":[{"url":"http://bit.ly/July12Q3","targetRectangle":{"y":660.3246459960938,"x":51.38669759324742,"width":406.9672504876088,"height":60.19161224365234}},{"url":"https://docs.google.com/forms/d/1YoHn9ZSm7vkP7Bhxiuvq4cTTfaLG9t4kUrGSaIV4p9g/edit?no_redirect%23responses","targetRectangle":{"y":649.3246459960938,"x":564.8246669362262,"width":340.3120003560632,"height":70.69601440429688}}],"accessibility":[{"text":"Answer it:","targetRectangle":{"y":597.3246459960938,"x":107.5546976773179,"width":294.6312503194679,"height":60.19161224365234}},{"text":"bit.ly/July12Q3 ","targetRectangle":{"y":660.3246459960938,"x":51.38669759324742,"width":422.0122505380514,"height":60.19161224365234}},{"text":"￼","targetRectangle":{"y":714,"x":499.4399998188019,"width":24.12,"height":21.99200439453125}},{"text":"Responses","targetRectangle":{"y":649.3246459960938,"x":564.8246669362262,"width":340.3120003560632,"height":70.69601440429688}},{"text":"What is the most likely diagnosis?","targetRectangle":{"y":27.94867504560489,"x":58.67999183081082,"width":928.6900011265279,"height":208.112032039644}},{"text":"A) Food allergy","targetRectangle":{"y":233.6623077392578,"x":83.78518979206656,"width":253.6563599999999,"height":49.80552520751951}},{"text":"B) Hereditary Angioedema","targetRectangle":{"y":284.6623077392578,"x":83.78518979206656,"width":442.08558,"height":73.50552585124967}},{"text":"C) Drug allergy","targetRectangle":{"y":359.362308382988,"x":83.78518979206656,"width":253.01646,"height":73.50552585124967}},{"text":"D) Chronic Urticaria with Angioedema","targetRectangle":{"y":434.0623090267181,"x":83.78518979206656,"width":636.9991199999999,"height":73.50552585124973}},{"text":"E) Acquired Angioedema","targetRectangle":{"y":508.7623096704483,"x":83.78518979206656,"width":412.90614,"height":73.50552585124979}}],"baseLayer":{"animations":[],"initialState":{"affineTransform":[1,0,0,1,0,0],"masksToBounds":false,"rotation":0,"scale":1,"position":{"pointX":512,"pointY":384},"width":1024,"sublayerTransform":[1,0,0,0,0,1,0,0,0,0,1,0,0,0,0,1],"contentsRect":{"y":0,"x":0,"width":1,"height":1},"opacity":1,"edgeAntialiasingMask":251658240,"height":768,"hidden":false,"anchorPoint":{"pointX":0.5,"pointY":0.5}},"objectID":"0","layers":[{"animations":[],"initialState":{"affineTransform":[1,0,0,1,0,0],"masksToBounds":false,"rotation":0,"scale":1,"position":{"pointX":512,"pointY":384},"width":1024,"sublayerTransform":[1,0,0,0,0,1,0,0,0,0,1,-0.0004922987690640373,0,0,0,1],"contentsRect":{"y":0,"x":0,"width":1,"height":1},"opacity":1,"edgeAntialiasingMask":251658240,"height":768,"hidden":false,"anchorPoint":{"pointX":0.5,"pointY":0.5}},"layers":[{"animations":[],"layers":[],"texturedRectangle":{"isBackgroundTexture":false,"singleTextureOpacity":1,"textureType":0,"textBaseline":0,"textXHeight":0,"isVerticalText":false},"initialState":{"affineTransform":[1,0,0,1,0,0],"masksToBounds":false,"rotation":0,"scale":1,"position":{"pointX":512,"pointY":384},"width":1024,"sublayerTransform":[1,0,0,0,0,1,0,0,0,0,1,0,0,0,0,1],"contentsRect":{"y":0,"x":0,"width":1,"height":1},"opacity":1,"edgeAntialiasingMask":0,"height":768,"hidden":false,"anchorPoint":{"pointX":0.5,"pointY":0.5}},"texture":"CDAECF3C4A226A6B0C3893C2DB2E3B05"}]}]}}]}